biogeme/.DS_Store
biogeme/README.txt
biogeme/__init__.py
biogeme/assisted.py
biogeme/audit_tuple.py
biogeme/biogeme.py
biogeme/biogeme.py.keep
biogeme/biogeme.pyi
biogeme/biogeme_logging.py
biogeme/check_parameters.py
biogeme/cnl.py
biogeme/constants.py
biogeme/default_parameters.py
biogeme/deprecated.py
biogeme/dict_of_formulas.py
biogeme/distributions.py
biogeme/exceptions.py
biogeme/expressions_registry.py
biogeme/filenames.py
biogeme/floating_point.py
biogeme/function_output.py
biogeme/loglikelihood.py
biogeme/lsh.py
biogeme/multiobjectives.py
biogeme/nests.py
biogeme/optimization.py
biogeme/parameters.py
biogeme/partition.py
biogeme/pymc_calculator.py
biogeme/results.py
biogeme/second_derivatives.py
biogeme/validity.py
biogeme/version.py
biogeme/bayesian_estimation/__init__.py
biogeme/bayesian_estimation/bayesian_results.py
biogeme/bayesian_estimation/check_shape.py
biogeme/bayesian_estimation/dimensions.py
biogeme/bayesian_estimation/html_output.py
biogeme/bayesian_estimation/pandas_output.py
biogeme/bayesian_estimation/raw_bayesian_results.py
biogeme/bayesian_estimation/sampling.py
biogeme/bayesian_estimation/sampling_strategy.py
biogeme/bayesian_estimation/__pycache__/__init__.cpython-313.pyc
biogeme/bayesian_estimation/__pycache__/bayesian_results.cpython-313.pyc
biogeme/bayesian_estimation/__pycache__/check_shape.cpython-313.pyc
biogeme/bayesian_estimation/__pycache__/html_output.cpython-313.pyc
biogeme/bayesian_estimation/__pycache__/pandas_output.cpython-313.pyc
biogeme/bayesian_estimation/__pycache__/raw_bayesian_results.cpython-313.pyc
biogeme/bayesian_estimation/__pycache__/sampling.cpython-313.pyc
biogeme/bayesian_estimation/__pycache__/sampling_strategy.cpython-313.pyc
biogeme/catalog/__init__.py
biogeme/catalog/catalog.py
biogeme/catalog/catalog_iterator.py
biogeme/catalog/central_controller.py
biogeme/catalog/configuration.py
biogeme/catalog/controller.py
biogeme/catalog/generic_alt_specific_catalog.py
biogeme/catalog/segmentation_catalog.py
biogeme-3.3.2.dist-info/licenses/LICENSE
biogeme-3.3.2.dist-info/METADATA
biogeme-3.3.2.dist-info/WHEEL
biogeme-3.3.2.dist-info/top_level.txt
biogeme-3.3.2.dist-info/RECORD
