Metadata-Version: 2.4
Name: biogeme
Version: 3.3.2
Summary: Estimation and application of discrete choice models
Author-email: Michel Bierlaire <michel.bierlaire@epfl.ch>
Project-URL: Homepage, https://biogeme.epfl.ch/sphinx/index.html
Project-URL: Documentation, https://biogeme.epfl.ch/sphinx/index.html
Project-URL: Code, https://github.com/michelbierlaire/biogeme
Classifier: Intended Audience :: Education
Classifier: Intended Audience :: Science/Research
Classifier: Topic :: Scientific/Engineering
Classifier: Topic :: Scientific/Engineering :: Mathematics
Classifier: Natural Language :: English
Classifier: Operating System :: OS Independent
Classifier: Programming Language :: C++
Classifier: Programming Language :: Cython
Classifier: Programming Language :: Python
Classifier: Programming Language :: Python :: 3
Classifier: Programming Language :: Python :: 3 :: Only
Classifier: Programming Language :: Python :: Implementation :: CPython
License-File: LICENSE
Requires-Dist: pandas<3,>=2.3.0
Requires-Dist: scipy<2,>=1.15.3
Requires-Dist: tqdm>=4.67.1
Requires-Dist: tomlkit>=0.13.3
Requires-Dist: python-levenshtein>=0.25.1
Requires-Dist: fuzzywuzzy>=0.18.0
Requires-Dist: biogeme_optimization<0.1,>=0.0.11
Requires-Dist: matplotlib<4,>=3.10.3
Requires-Dist: numpy<3,>=2.2.6
Requires-Dist: ipython>=8.37.0
Requires-Dist: Jinja2>=3.1.4
Requires-Dist: PyYAML>=6.0.2
Requires-Dist: jax>=0.6.2
Requires-Dist: tabulate>=0.9.0
Requires-Dist: joblib>=1.5.1
Requires-Dist: tqdm_joblib>=0.0.4
Requires-Dist: pymc>=5.25.1
Requires-Dist: numpyro>=0.19.0
Requires-Dist: h5netcdf>=1.7.3
Requires-Dist: h5py>=3.15.1
Provides-Extra: testing
Requires-Dist: pytest>=7.2.0; extra == "testing"
Requires-Dist: pytest-cov>=4.0.0; extra == "testing"
Requires-Dist: tox>=3.27.1; extra == "testing"
Dynamic: license-file
